[
    {
        "open_time": "2026-04-15 12:00:00+07:00",
        "open": 616.04,
        "high": 616.98,
        "low": 613.76,
        "close": 614.07,
        "volume": "1869.05",
        "close_time": "2026-04-15 12:59:59.999000+07:00",
        "quote_asset_volume": "1149195.43810",
        "num_trades": 4219,
        "taker_buy_base_volume": "755.45",
        "taker_buy_quote_volume": "464517.24610",
        "ignore": "0",
        "current_price": 614.07
    },
    {
        "open_time": "2026-04-15 13:00:00+07:00",
        "open": 614.08,
        "high": 615.73,
        "low": 613.48,
        "close": 614.87,
        "volume": "958.59",
        "close_time": "2026-04-15 13:59:59.999000+07:00",
        "quote_asset_volume": "589442.96950",
        "num_trades": 3300,
        "taker_buy_base_volume": "538.16",
        "taker_buy_quote_volume": "330926.18120",
        "ignore": "0",
        "current_price": 614.87
    },
    {
        "open_time": "2026-04-15 14:00:00+07:00",
        "open": 614.86,
        "high": 615.29,
        "low": 611.39,
        "close": 612.26,
        "volume": "3256.35",
        "close_time": "2026-04-15 14:59:59.999000+07:00",
        "quote_asset_volume": "1995621.01180",
        "num_trades": 6362,
        "taker_buy_base_volume": "1705.12",
        "taker_buy_quote_volume": "1044730.28760",
        "ignore": "0",
        "current_price": 612.26
    },
    {
        "open_time": "2026-04-15 15:00:00+07:00",
        "open": 612.27,
        "high": 615.52,
        "low": 611.14,
        "close": 615.13,
        "volume": "2406.07",
        "close_time": "2026-04-15 15:59:59.999000+07:00",
        "quote_asset_volume": "1475223.51820",
        "num_trades": 5778,
        "taker_buy_base_volume": "1189.80",
        "taker_buy_quote_volume": "729458.71880",
        "ignore": "0",
        "current_price": 615.13
    },
    {
        "open_time": "2026-04-15 16:00:00+07:00",
        "open": 615.13,
        "high": 616.52,
        "low": 614.39,
        "close": 616.21,
        "volume": "1382.07",
        "close_time": "2026-04-15 16:59:59.999000+07:00",
        "quote_asset_volume": "850759.79670",
        "num_trades": 4272,
        "taker_buy_base_volume": "631.37",
        "taker_buy_quote_volume": "388688.18610",
        "ignore": "0",
        "current_price": 616.21
    },
    {
        "open_time": "2026-04-15 17:00:00+07:00",
        "open": 616.19,
        "high": 619.3,
        "low": 616.11,
        "close": 617.69,
        "volume": "3528.40",
        "close_time": "2026-04-15 17:59:59.999000+07:00",
        "quote_asset_volume": "2180524.90840",
        "num_trades": 6585,
        "taker_buy_base_volume": "1738.75",
        "taker_buy_quote_volume": "1074407.13760",
        "ignore": "0",
        "current_price": 617.69
    },
    {
        "open_time": "2026-04-15 18:00:00+07:00",
        "open": 617.74,
        "high": 621.46,
        "low": 617.73,
        "close": 620.47,
        "volume": "4189.33",
        "close_time": "2026-04-15 18:59:59.999000+07:00",
        "quote_asset_volume": "2596163.69180",
        "num_trades": 5525,
        "taker_buy_base_volume": "2090.44",
        "taker_buy_quote_volume": "1295562.99840",
        "ignore": "0",
        "current_price": 620.47
    },
    {
        "open_time": "2026-04-15 19:00:00+07:00",
        "open": 620.46,
        "high": 620.46,
        "low": 618.28,
        "close": 618.84,
        "volume": "3175.85",
        "close_time": "2026-04-15 19:59:59.999000+07:00",
        "quote_asset_volume": "1966487.57850",
        "num_trades": 4912,
        "taker_buy_base_volume": "1648.12",
        "taker_buy_quote_volume": "1020498.15390",
        "ignore": "0",
        "current_price": 618.84
    },
    {
        "open_time": "2026-04-15 20:00:00+07:00",
        "open": 618.83,
        "high": 619.95,
        "low": 617.27,
        "close": 619.71,
        "volume": "4021.13",
        "close_time": "2026-04-15 20:59:59.999000+07:00",
        "quote_asset_volume": "2487297.33380",
        "num_trades": 7114,
        "taker_buy_base_volume": "1576.11",
        "taker_buy_quote_volume": "975068.64410",
        "ignore": "0",
        "current_price": 619.71
    },
    {
        "open_time": "2026-04-15 21:00:00+07:00",
        "open": 619.7,
        "high": 621.15,
        "low": 617.52,
        "close": 619.22,
        "volume": "4162.69",
        "close_time": "2026-04-15 21:59:59.999000+07:00",
        "quote_asset_volume": "2579507.61140",
        "num_trades": 7250,
        "taker_buy_base_volume": "1555.19",
        "taker_buy_quote_volume": "963870.65450",
        "ignore": "0",
        "current_price": 619.22
    }
]